ovkfusion/__init__.py
ovkfusion/account.py
ovkfusion/audio.py
ovkfusion/auth.py
ovkfusion/board.py
ovkfusion/config.py
ovkfusion/docs.py
ovkfusion/friends.py
ovkfusion/gifts.py
ovkfusion/groups.py
ovkfusion/likes.py
ovkfusion/messages.py
ovkfusion/newsfeed.py
ovkfusion/notes.py
ovkfusion/notifications.py
ovkfusion/ovk.py
ovkfusion/pay.py
ovkfusion/photos.py
ovkfusion/polls.py
ovkfusion/reports.py
ovkfusion/status.py
ovkfusion/users.py
ovkfusion/utils.py
ovkfusion/video.py
ovkfusion/wall.py
OVKFusion-0.1.0.dist-info/LICENSE
OVKFusion-0.1.0.dist-info/METADATA
OVKFusion-0.1.0.dist-info/WHEEL
OVKFusion-0.1.0.dist-info/top_level.txt
OVKFusion-0.1.0.dist-info/RECORD
