Metadata-Version: 2.2
Name: OVKFusion
Version: 0.1.0
Summary: A Python library for interacting with OVK.to platform
Home-page: https://github.com/KailUser/ovkfusion
Author: Syirezz Cheese
Author-email: syirezz@example.com
Classifier: Programming Language :: Python :: 3
Classifier: License :: OSI Approved :: MIT License
Classifier: Operating System :: OS Independent
Requires-Python: >=3.7
License-File: LICENSE
Requires-Dist: requests
Dynamic: author
Dynamic: author-email
Dynamic: classifier
Dynamic: description
Dynamic: description-content-type
Dynamic: home-page
Dynamic: requires-dist
Dynamic: requires-python
Dynamic: summary
